!
.travis.yml
NOTICE.txt
README.rst
bootstrap.py
buildout.cfg
eke.study.sublime-project
setup.cfg
setup.py
travis.cfg
docs/HISTORY.txt
docs/INSTALL.txt
docs/LICENSE.txt
eke/__init__.py
eke.study.egg-info/PKG-INFO
eke.study.egg-info/SOURCES.txt
eke.study.egg-info/dependency_links.txt
eke.study.egg-info/entry_points.txt
eke.study.egg-info/namespace_packages.txt
eke.study.egg-info/not-zip-safe
eke.study.egg-info/requires.txt
eke.study.egg-info/top_level.txt
eke/study/README.rst
eke/study/__init__.py
eke/study/config.py
eke/study/configure.zcml
eke/study/interfaces.py
eke/study/overrides.zcml
eke/study/testing.py
eke/study/upgrades.py
eke/study/upgrades.zcml
eke/study/utils.py
eke/study/browser/__init__.py
eke/study/browser/configure.zcml
eke/study/browser/rdf.py
eke/study/browser/views.py
eke/study/browser/images/nonEDRNProtocol.png
eke/study/browser/images/protocol.gif
eke/study/browser/images/study-folder.gif
eke/study/browser/images/teamProject.png
eke/study/browser/stylesheets/protocol.css
eke/study/browser/templates/protocol.pt
eke/study/browser/templates/studyfolder.pt
eke/study/content/__init__.py
eke/study/content/configure.zcml
eke/study/content/protocol.py
eke/study/content/studyfolder.py
eke/study/profiles/default/catalog.xml
eke/study/profiles/default/factorytool.xml
eke/study/profiles/default/metadata.xml
eke/study/profiles/default/rolemap.xml
eke/study/profiles/default/types.xml
eke/study/profiles/default/types/Protocol.xml
eke/study/profiles/default/types/Study_Folder.xml
eke/study/tests/__init__.py
eke/study/tests/base.py
eke/study/tests/testDoctest.py
eke/study/tests/testSetup.py