Metadata-Version: 2.1
Name: eke.study
Version: 1.1.18
Summary: Study and protocol information for the EDRN Knowledge Environment
Home-page: https://github.com/EDRN/eke.study
Author: Sean Kelly
Author-email: sean.kelly@jpl.nasa.gov
License: ALv2
Keywords: web zope plone edrn cancer biomarkers eke study protocol
Platform: UNKNOWN
Classifier: Development Status :: 4 - Beta
Classifier: Environment :: Web Environment
Classifier: Framework :: Plone
Classifier: Intended Audience :: Healthcare Industry
Classifier: Intended Audience :: Science/Research
Classifier: License :: Other/Proprietary License
Classifier: License :: OSI Approved :: Apache Software License
Classifier: Programming Language :: Python
Classifier: Topic :: Internet :: WWW/HTTP
Classifier: Topic :: Scientific/Engineering :: Bio-Informatics
Classifier: Topic :: Software Development :: Libraries :: Python Modules
Provides-Extra: test
